pdfnumbering/__init__.py
pdfnumbering/cli.py
pdfnumbering/color.py
pdfnumbering/core.py
pdfnumbering-0.1.1.dist-info/LICENSE
pdfnumbering-0.1.1.dist-info/METADATA
pdfnumbering-0.1.1.dist-info/WHEEL
pdfnumbering-0.1.1.dist-info/entry_points.txt
pdfnumbering-0.1.1.dist-info/top_level.txt
pdfnumbering-0.1.1.dist-info/RECORD
