Metadata-Version: 2.1
Name: pdfnumbering
Version: 0.1.1
Summary: A package and CLI for adding page numbering to PDFs
Author-email: Mikko Marttila <mikkmart@protonmail.com>
Project-URL: Source, https://github.com/mikmart/pdfnumbering
Project-URL: Bug Reports, https://github.com/mikmart/pdfnumbering/issues
Classifier: Programming Language :: Python :: 3
Classifier: License :: OSI Approved :: MIT License
Classifier: Operating System :: OS Independent
Requires-Python: >=3.10
License-File: LICENSE
Requires-Dist: fpdf2
Requires-Dist: pypdf
